gitstack_helper/__init__.py
gitstack_helper/main.py
gitstack_helper/prompts.py
gitstack_helper-2025.12.21100148.dist-info/METADATA
gitstack_helper-2025.12.21100148.dist-info/WHEEL
gitstack_helper-2025.12.21100148.dist-info/top_level.txt
gitstack_helper-2025.12.21100148.dist-info/RECORD
