Metadata-Version: 2.4
Name: gitstack-helper
Version: 2025.12.21100148
Summary: A new package that helps developers manage and organize their Git branches and commit stacks more efficiently. It takes a description of the current branch state or a developer's intended changes as i
Author-email: gitstack-helper <hi@eugene.plus>
License: MIT
Project-URL: Homepage, https://github.com/chigwell/gitstack-helper
Requires-Python: >=3.9
Requires-Dist: langchain-llm7>=0.0.0
Requires-Dist: llmatch-messages>=0.0.0
Requires-Dist: langchain-core>=0.3.0
